ipckit-0.1.3.dist-info/METADATA
ipckit-0.1.3.dist-info/WHEEL
ipckit-0.1.3.dist-info/licenses/LICENSE-APACHE
ipckit-0.1.3.dist-info/licenses/LICENSE-MIT
ipckit/__init__.py
ipckit/__init__.pyi
ipckit/ipckit.abi3.so
ipckit/py.typed
ipckit-0.1.3.dist-info/RECORD
